LICENSE
MANIFEST.in
README.md
setup.py
src/ea_agents/VERSION
src/ea_agents/__init__.py
src/ea_agents/agent.py
src/ea_agents/handler.py
src/ea_agents/main.py
src/ea_agents/settings.ini
src/ea_agents/libs/FifoQueue.py
src/ea_agents/libs/__init__.py
src/ea_agents/libs/settings.py
src/ea_agents/libs/NetLayerLib/ClientAgent.py
src/ea_agents/libs/NetLayerLib/FifoCallBack.py
src/ea_agents/libs/NetLayerLib/Messages.py
src/ea_agents/libs/NetLayerLib/TcpClient.py
src/ea_agents/libs/NetLayerLib/TransactionManager.py
src/ea_agents/libs/NetLayerLib/WebSocket.py
src/ea_agents/libs/NetLayerLib/__init__.py
src/ea_agents/plugins/__init__.py
src/ea_agents/var/__init__.py
src/ea_agents/var/data/__init__.py
src/ea_agents/var/logs/__init__.py
src/extensiveautomation_agent.egg-info/PKG-INFO
src/extensiveautomation_agent.egg-info/SOURCES.txt
src/extensiveautomation_agent.egg-info/dependency_links.txt
src/extensiveautomation_agent.egg-info/entry_points.txt
src/extensiveautomation_agent.egg-info/top_level.txt