Metadata-Version: 2.1
Name: extensiveautomation-agent
Version: 16.2.0
Summary: Remote agent for the extensiveautomation server
Home-page: https://www.extensiveautomation.org/
Author: Denis MACHARD
Author-email: d.machard@gmail.com
Keywords: extensiveautomation agent
Platform: any
Classifier: License :: OSI Approved :: GNU Lesser General Public License v2 or later (LGPLv2+)
Classifier: Programming Language :: Python :: 3
Classifier: Operating System :: OS Independent
Classifier: Topic :: Software Development :: Testing
Classifier: Topic :: Software Development :: Testing :: Acceptance
License-File: LICENSE
